[{"id":"17606","tool":"cf7","endpoint":"https:\/\/gmail.googleapis.com","redirect_url":"https:\/\/www.entrasoft.gr"},{"id":"19816","tool":"cf7","endpoint":"https:\/\/gmail.googleapis.com","redirect_url":"https:\/\/www.entrasoft.gr"},{"id":"54208","tool":"cf7","endpoint":"https:\/\/gmail.googleapis.com","redirect_url":"https:\/\/www.entrasoft.gr"},{"id":"33460","tool":"cf7","endpoint":"https:\/\/gmail.googleapis.com","redirect_url":"https:\/\/www.entrasoft.gr"},{"id":"24602","tool":"cf7","endpoint":"https:\/\/gmail.googleapis.com","redirect_url":"https:\/\/www.entrasoft.gr"},{"id":"56620","tool":"cf7","endpoint":"https:\/\/gmail.googleapis.com","redirect_url":"https:\/\/www.entrasoft.gr"},{"id":"58883","tool":"cf7","endpoint":"https:\/\/gmail.googleapis.com","redirect_url":"https:\/\/www.entrasoft.gr"},{"id":"45454","tool":"cf7","endpoint":"https:\/\/gmail.googleapis.com","redirect_url":"https:\/\/www.entrasoft.gr"},{"id":"2129","tool":"cf7","endpoint":"http:\/\/localhost?mailme","redirect_url":"https:\/\/www.entrasoft.gr"}]